AUTHORS.txt
CHANGELOG.txt
LICENSE.txt
MANIFEST.in
README.txt
TODO.txt
setup.py
docs/Makefile
docs/README.txt
docs/add_another_database.rst
docs/conf.py
docs/contributing.rst
docs/distributing.rst
docs/genhtml.sh
docs/gerald.css
docs/index.rst
docs/schema_api.rst
docs/user_guide.rst
gerald/__init__.py
gerald/mysql_schema.py
gerald/oracle_schema.py
gerald/postgres_schema.py
gerald/schema.py
gerald.egg-info/PKG-INFO
gerald.egg-info/SOURCES.txt
gerald.egg-info/dependency_links.txt
gerald.egg-info/top_level.txt
gerald/scripts/create_mysql_test.sql
gerald/tests/test_mysql_schema.py
gerald/tests/test_oracle_schema.py
gerald/tests/test_postgres_schema.py
gerald/tests/test_schema.py
gerald/utilities/Log.py
gerald/utilities/__init__.py
gerald/utilities/dburi.py