Metadata-Version: 1.0
Name: gerald
Version: 0.4.1.1
Summary: Gerald database schema management utility
Home-page: http://halfcooked.com/code/gerald/
Author: Andrew J Todd esq.
Author-email: andy47@halfcooked.com
License: BSD
Download-URL: http://pypi.python.org/pypi/gerald
Platform: UNKNOWN
